{
    "name": "Keppel, Keith",
    "machine_name": "keppel_keith",
    "type": "nursery",
    "retail_wholesale": {
        "retail": true,
        "wholesale": false
    },
    "location": {
        "country": {
            "united_states": true,
            "canada": false
        },
        "address_1": "PO Box 18154",
        "address_2": "",
        "city": "Salem",
        "state": "OR",
        "postal_code": "97305",
        "geo_coordinate": "POINT (-123.0350963 44.9428975)"
    },
    "contact": {
        "website": {
            "url": "http:\/\/www.keithkeppeliris.com",
            "title": null,
            "attributes": []
        },
        "email": null,
        "phone": "503-391-9241",
        "fax": null,
        "name": null
    },
    "specialties": [
        {
            "machine_name": "iris",
            "type": "nursery_category",
            "archival_data": {
                "id": "216172"
            }
        }
    ],
    "catalog": {
        "print": true,
        "online": true,
        "web_only": false
    },
    "update": "2018",
    "nursery_catalog_items": [
        {
            "name": "Keith Keppel 2018",
            "machine_name": "keith_keppel_2018",
            "type": "nursery_catalog",
            "date": "Apr 11 2018",
            "nursery": "keppel_keith",
            "active": true,
            "plants": [
                {
                    "reference": "1669392",
                    "machine_name": "iris_cultivars_another_suggestion",
                    "type": "variety",
                    "seed": false,
                    "pages": null,
                    "active": false,
                    "notes": null,
                    "archival_data": {
                        "id": "899471",
                        "fgsid": null,
                        "legacy_id": null,
                        "catalog_source_id": null
                    }
                },
                {
                    "reference": "1669390",
                    "machine_name": "iris_cultivars_black_lipstick",
                    "type": "variety",
                    "seed": false,
                    "pages": null,
                    "active": false,
                    "notes": null,
                    "archival_data": {
                        "id": "899476",
                        "fgsid": null,
                        "legacy_id": null,
                        "catalog_source_id": null
                    }
                },
                {
                    "reference": "1669391",
                    "machine_name": "iris_cultivars_blind_ambition",
                    "type": "variety",
                    "seed": false,
                    "pages": null,
                    "active": false,
                    "notes": null,
                    "archival_data": {
                        "id": "899481",
                        "fgsid": null,
                        "legacy_id": null,
                        "catalog_source_id": null
                    }
                },
                {
                    "reference": "1669388",
                    "machine_name": "iris_cultivars_dark_energy",
                    "type": "variety",
                    "seed": false,
                    "pages": null,
                    "active": false,
                    "notes": null,
                    "archival_data": {
                        "id": "899486",
                        "fgsid": null,
                        "legacy_id": null,
                        "catalog_source_id": null
                    }
                },
                {
                    "reference": "1669472",
                    "machine_name": "iris_cultivars_flash_mob",
                    "type": "variety",
                    "seed": false,
                    "pages": null,
                    "active": false,
                    "notes": null,
                    "archival_data": {
                        "id": "899491",
                        "fgsid": null,
                        "legacy_id": null,
                        "catalog_source_id": null
                    }
                },
                {
                    "reference": "1669473",
                    "machine_name": "iris_cultivars_idle_rich",
                    "type": "variety",
                    "seed": false,
                    "pages": null,
                    "active": false,
                    "notes": null,
                    "archival_data": {
                        "id": "899496",
                        "fgsid": null,
                        "legacy_id": null,
                        "catalog_source_id": null
                    }
                },
                {
                    "reference": "1669471",
                    "machine_name": "iris_cultivars_ghirardelli_square",
                    "type": "variety",
                    "seed": false,
                    "pages": null,
                    "active": false,
                    "notes": null,
                    "archival_data": {
                        "id": "899501",
                        "fgsid": null,
                        "legacy_id": null,
                        "catalog_source_id": null
                    }
                },
                {
                    "reference": "1669474",
                    "machine_name": "iris_cultivars_foreign_agent",
                    "type": "variety",
                    "seed": false,
                    "pages": null,
                    "active": false,
                    "notes": null,
                    "archival_data": {
                        "id": "899506",
                        "fgsid": null,
                        "legacy_id": null,
                        "catalog_source_id": null
                    }
                },
                {
                    "reference": "1669389",
                    "machine_name": "iris_cultivars_mixed_signals",
                    "type": "variety",
                    "seed": false,
                    "pages": null,
                    "active": false,
                    "notes": null,
                    "archival_data": {
                        "id": "899511",
                        "fgsid": null,
                        "legacy_id": null,
                        "catalog_source_id": null
                    }
                },
                {
                    "reference": "2297046",
                    "machine_name": "iris_cultivars_brass_lamp",
                    "type": "variety",
                    "seed": false,
                    "pages": null,
                    "active": false,
                    "notes": null,
                    "archival_data": {
                        "id": "899516",
                        "fgsid": null,
                        "legacy_id": null,
                        "catalog_source_id": null
                    }
                },
                {
                    "reference": "2297051",
                    "machine_name": "iris_cultivars_catch_the_fever",
                    "type": "variety",
                    "seed": false,
                    "pages": null,
                    "active": false,
                    "notes": null,
                    "archival_data": {
                        "id": "899521",
                        "fgsid": null,
                        "legacy_id": null,
                        "catalog_source_id": null
                    }
                },
                {
                    "reference": "2297056",
                    "machine_name": "iris_cultivars_clean_energy",
                    "type": "variety",
                    "seed": false,
                    "pages": null,
                    "active": false,
                    "notes": null,
                    "archival_data": {
                        "id": "899526",
                        "fgsid": null,
                        "legacy_id": null,
                        "catalog_source_id": null
                    }
                },
                {
                    "reference": "2297061",
                    "machine_name": "iris_cultivars_edwardian_era",
                    "type": "variety",
                    "seed": false,
                    "pages": null,
                    "active": false,
                    "notes": null,
                    "archival_data": {
                        "id": "899531",
                        "fgsid": null,
                        "legacy_id": null,
                        "catalog_source_id": null
                    }
                },
                {
                    "reference": "2297066",
                    "machine_name": "iris_cultivars_game_changer",
                    "type": "variety",
                    "seed": false,
                    "pages": null,
                    "active": false,
                    "notes": null,
                    "archival_data": {
                        "id": "899536",
                        "fgsid": null,
                        "legacy_id": null,
                        "catalog_source_id": null
                    }
                },
                {
                    "reference": "2297071",
                    "machine_name": "iris_cultivars_inkblot",
                    "type": "variety",
                    "seed": false,
                    "pages": null,
                    "active": false,
                    "notes": null,
                    "archival_data": {
                        "id": "899541",
                        "fgsid": null,
                        "legacy_id": null,
                        "catalog_source_id": null
                    }
                },
                {
                    "reference": "2297076",
                    "machine_name": "iris_cultivars_major_issue",
                    "type": "variety",
                    "seed": false,
                    "pages": null,
                    "active": false,
                    "notes": null,
                    "archival_data": {
                        "id": "899546",
                        "fgsid": null,
                        "legacy_id": null,
                        "catalog_source_id": null
                    }
                },
                {
                    "reference": "2297081",
                    "machine_name": "iris_cultivars_mendacity",
                    "type": "variety",
                    "seed": false,
                    "pages": null,
                    "active": false,
                    "notes": null,
                    "archival_data": {
                        "id": "899551",
                        "fgsid": null,
                        "legacy_id": null,
                        "catalog_source_id": null
                    }
                },
                {
                    "reference": "2297086",
                    "machine_name": "iris_cultivars_panjandrum",
                    "type": "variety",
                    "seed": false,
                    "pages": null,
                    "active": false,
                    "notes": null,
                    "archival_data": {
                        "id": "899556",
                        "fgsid": null,
                        "legacy_id": null,
                        "catalog_source_id": null
                    }
                },
                {
                    "reference": "2297091",
                    "machine_name": "iris_cultivars_shadowed_light",
                    "type": "variety",
                    "seed": false,
                    "pages": null,
                    "active": false,
                    "notes": null,
                    "archival_data": {
                        "id": "899561",
                        "fgsid": null,
                        "legacy_id": null,
                        "catalog_source_id": null
                    }
                },
                {
                    "reference": "2297096",
                    "machine_name": "iris_cultivars_shandygaff",
                    "type": "variety",
                    "seed": false,
                    "pages": null,
                    "active": false,
                    "notes": null,
                    "archival_data": {
                        "id": "899566",
                        "fgsid": null,
                        "legacy_id": null,
                        "catalog_source_id": null
                    }
                },
                {
                    "reference": "2297101",
                    "machine_name": "iris_cultivars_space_signal",
                    "type": "variety",
                    "seed": false,
                    "pages": null,
                    "active": false,
                    "notes": null,
                    "archival_data": {
                        "id": "899571",
                        "fgsid": null,
                        "legacy_id": null,
                        "catalog_source_id": null
                    }
                },
                {
                    "reference": "2297106",
                    "machine_name": "iris_cultivars_sugar_high",
                    "type": "variety",
                    "seed": false,
                    "pages": null,
                    "active": false,
                    "notes": null,
                    "archival_data": {
                        "id": "899576",
                        "fgsid": null,
                        "legacy_id": null,
                        "catalog_source_id": null
                    }
                },
                {
                    "reference": "2297111",
                    "machine_name": "iris_cultivars_costume_jewelry",
                    "type": "variety",
                    "seed": false,
                    "pages": null,
                    "active": false,
                    "notes": null,
                    "archival_data": {
                        "id": "899581",
                        "fgsid": null,
                        "legacy_id": null,
                        "catalog_source_id": null
                    }
                },
                {
                    "reference": "2297116",
                    "machine_name": "iris_cultivars_sorbet_swirl",
                    "type": "variety",
                    "seed": false,
                    "pages": null,
                    "active": false,
                    "notes": null,
                    "archival_data": {
                        "id": "899586",
                        "fgsid": null,
                        "legacy_id": null,
                        "catalog_source_id": null
                    }
                },
                {
                    "reference": "2297121",
                    "machine_name": "iris_cultivars_dalriada",
                    "type": "variety",
                    "seed": false,
                    "pages": null,
                    "active": false,
                    "notes": null,
                    "archival_data": {
                        "id": "899591",
                        "fgsid": null,
                        "legacy_id": null,
                        "catalog_source_id": null
                    }
                },
                {
                    "reference": "2297131",
                    "machine_name": "iris_cultivars_baltimore",
                    "type": "variety",
                    "seed": false,
                    "pages": null,
                    "active": false,
                    "notes": null,
                    "archival_data": {
                        "id": "899596",
                        "fgsid": null,
                        "legacy_id": null,
                        "catalog_source_id": null
                    }
                },
                {
                    "reference": "2297126",
                    "machine_name": "iris_cultivars_adriatic_noble",
                    "type": "variety",
                    "seed": false,
                    "pages": null,
                    "active": false,
                    "notes": null,
                    "archival_data": {
                        "id": "899601",
                        "fgsid": null,
                        "legacy_id": null,
                        "catalog_source_id": null
                    }
                },
                {
                    "reference": "2297146",
                    "machine_name": "iris_cultivars_cosmic_voyage",
                    "type": "variety",
                    "seed": false,
                    "pages": null,
                    "active": false,
                    "notes": null,
                    "archival_data": {
                        "id": "899606",
                        "fgsid": null,
                        "legacy_id": null,
                        "catalog_source_id": null
                    }
                },
                {
                    "reference": "2297151",
                    "machine_name": "iris_cultivars_desert_trails",
                    "type": "variety",
                    "seed": false,
                    "pages": null,
                    "active": false,
                    "notes": null,
                    "archival_data": {
                        "id": "899611",
                        "fgsid": null,
                        "legacy_id": null,
                        "catalog_source_id": null
                    }
                },
                {
                    "reference": "2297156",
                    "machine_name": "iris_cultivars_imperial_guard",
                    "type": "variety",
                    "seed": false,
                    "pages": null,
                    "active": false,
                    "notes": null,
                    "archival_data": {
                        "id": "899616",
                        "fgsid": null,
                        "legacy_id": null,
                        "catalog_source_id": null
                    }
                },
                {
                    "reference": "2297191",
                    "machine_name": "iris_cultivars_smoky_dusk",
                    "type": "variety",
                    "seed": false,
                    "pages": null,
                    "active": false,
                    "notes": null,
                    "archival_data": {
                        "id": "899621",
                        "fgsid": null,
                        "legacy_id": null,
                        "catalog_source_id": null
                    }
                },
                {
                    "reference": "2297186",
                    "machine_name": "iris_cultivars_royalty_remembered",
                    "type": "variety",
                    "seed": false,
                    "pages": null,
                    "active": false,
                    "notes": null,
                    "archival_data": {
                        "id": "899626",
                        "fgsid": null,
                        "legacy_id": null,
                        "catalog_source_id": null
                    }
                },
                {
                    "reference": "2297181",
                    "machine_name": "iris_cultivars_restless_spirit",
                    "type": "variety",
                    "seed": false,
                    "pages": null,
                    "active": false,
                    "notes": null,
                    "archival_data": {
                        "id": "899631",
                        "fgsid": null,
                        "legacy_id": null,
                        "catalog_source_id": null
                    }
                },
                {
                    "reference": "2297176",
                    "machine_name": "iris_cultivars_ocean_liner",
                    "type": "variety",
                    "seed": false,
                    "pages": null,
                    "active": false,
                    "notes": null,
                    "archival_data": {
                        "id": "899636",
                        "fgsid": null,
                        "legacy_id": null,
                        "catalog_source_id": null
                    }
                },
                {
                    "reference": "2297171",
                    "machine_name": "iris_cultivars_mood_ring",
                    "type": "variety",
                    "seed": false,
                    "pages": null,
                    "active": false,
                    "notes": null,
                    "archival_data": {
                        "id": "899641",
                        "fgsid": null,
                        "legacy_id": null,
                        "catalog_source_id": null
                    }
                },
                {
                    "reference": "2297166",
                    "machine_name": "iris_cultivars_marital_bliss",
                    "type": "variety",
                    "seed": false,
                    "pages": null,
                    "active": false,
                    "notes": null,
                    "archival_data": {
                        "id": "899646",
                        "fgsid": null,
                        "legacy_id": null,
                        "catalog_source_id": null
                    }
                },
                {
                    "reference": "2297161",
                    "machine_name": "iris_cultivars_margin_call",
                    "type": "variety",
                    "seed": false,
                    "pages": null,
                    "active": false,
                    "notes": null,
                    "archival_data": {
                        "id": "899651",
                        "fgsid": null,
                        "legacy_id": null,
                        "catalog_source_id": null
                    }
                },
                {
                    "reference": "2297196",
                    "machine_name": "iris_cultivars_sunset_boulevard",
                    "type": "variety",
                    "seed": false,
                    "pages": null,
                    "active": false,
                    "notes": null,
                    "archival_data": {
                        "id": "899656",
                        "fgsid": null,
                        "legacy_id": null,
                        "catalog_source_id": null
                    }
                },
                {
                    "reference": "2297201",
                    "machine_name": "iris_cultivars_vista_point",
                    "type": "variety",
                    "seed": false,
                    "pages": null,
                    "active": false,
                    "notes": null,
                    "archival_data": {
                        "id": "899661",
                        "fgsid": null,
                        "legacy_id": null,
                        "catalog_source_id": null
                    }
                },
                {
                    "reference": "2297111",
                    "machine_name": "iris_cultivars_costume_jewelry",
                    "type": "variety",
                    "seed": false,
                    "pages": null,
                    "active": false,
                    "notes": null,
                    "archival_data": {
                        "id": "899666",
                        "fgsid": null,
                        "legacy_id": null,
                        "catalog_source_id": null
                    }
                },
                {
                    "reference": "2297601",
                    "machine_name": "iris_cultivars_boondoggle",
                    "type": "variety",
                    "seed": false,
                    "pages": null,
                    "active": false,
                    "notes": null,
                    "archival_data": {
                        "id": "899671",
                        "fgsid": null,
                        "legacy_id": null,
                        "catalog_source_id": null
                    }
                },
                {
                    "reference": "2297116",
                    "machine_name": "iris_cultivars_sorbet_swirl",
                    "type": "variety",
                    "seed": false,
                    "pages": null,
                    "active": false,
                    "notes": null,
                    "archival_data": {
                        "id": "899676",
                        "fgsid": null,
                        "legacy_id": null,
                        "catalog_source_id": null
                    }
                },
                {
                    "reference": "2297121",
                    "machine_name": "iris_cultivars_dalriada",
                    "type": "variety",
                    "seed": false,
                    "pages": null,
                    "active": false,
                    "notes": null,
                    "archival_data": {
                        "id": "899681",
                        "fgsid": null,
                        "legacy_id": null,
                        "catalog_source_id": null
                    }
                },
                {
                    "reference": "2297206",
                    "machine_name": "iris_cultivars_arson",
                    "type": "variety",
                    "seed": false,
                    "pages": null,
                    "active": false,
                    "notes": null,
                    "archival_data": {
                        "id": "899686",
                        "fgsid": null,
                        "legacy_id": null,
                        "catalog_source_id": null
                    }
                },
                {
                    "reference": "2297211",
                    "machine_name": "iris_cultivars_unbroken_promise",
                    "type": "variety",
                    "seed": false,
                    "pages": null,
                    "active": false,
                    "notes": null,
                    "archival_data": {
                        "id": "899691",
                        "fgsid": null,
                        "legacy_id": null,
                        "catalog_source_id": null
                    }
                },
                {
                    "reference": "2297216",
                    "machine_name": "iris_cultivars_marsh_mist",
                    "type": "variety",
                    "seed": false,
                    "pages": null,
                    "active": false,
                    "notes": null,
                    "archival_data": {
                        "id": "899696",
                        "fgsid": null,
                        "legacy_id": null,
                        "catalog_source_id": null
                    }
                },
                {
                    "reference": "2297391",
                    "machine_name": "iris_cultivars_dark_triad",
                    "type": "variety",
                    "seed": false,
                    "pages": null,
                    "active": false,
                    "notes": null,
                    "archival_data": {
                        "id": "899701",
                        "fgsid": null,
                        "legacy_id": null,
                        "catalog_source_id": null
                    }
                }
            ]
        }
    ],
    "archival_data": {
        "id": "1673298",
        "legacy_id": "22209",
        "ships": true,
        "NODATE": false,
        "NoCatalog": false,
        "active": true,
        "bulkmail": false,
        "SRCE2000": "2018, 2015",
        "author": "oitadmin",
        "created": "1474897980"
    }
}
