{
    "name": "FGL Dahlias",
    "machine_name": "fgl_dahlias",
    "type": "nursery",
    "retail_wholesale": {
        "retail": true,
        "wholesale": false
    },
    "location": {
        "country": {
            "united_states": false,
            "canada": true
        },
        "address_1": "688 Charbonneau",
        "address_2": "",
        "city": "St-Lazare",
        "state": "QC",
        "postal_code": "J7T 2B3",
        "geo_coordinate": "POINT (-74.096942 45.375907)"
    },
    "contact": {
        "website": {
            "url": "http:\/\/fgldahlias.com\/",
            "title": null,
            "attributes": []
        },
        "email": null,
        "phone": "450-455-4831",
        "fax": null,
        "name": null
    },
    "specialties": [
        {
            "machine_name": "dahlias",
            "type": "nursery_category",
            "archival_data": {
                "id": "216160"
            }
        }
    ],
    "catalog": {
        "print": false,
        "online": true,
        "web_only": true
    },
    "update": null,
    "nursery_catalog_items": [],
    "archival_data": {
        "id": "1673687",
        "legacy_id": "25269",
        "ships": true,
        "NODATE": false,
        "NoCatalog": true,
        "active": true,
        "bulkmail": false,
        "SRCE2000": null,
        "author": "oitadmin",
        "created": "1474897980"
    }
}
