{
    "name": "Cold Creek Nurseries, Inc",
    "machine_name": "cold_creek_nurseries_inc",
    "type": "nursery",
    "retail_wholesale": {
        "retail": false,
        "wholesale": true
    },
    "location": {
        "country": {
            "united_states": true,
            "canada": false
        },
        "address_1": "398 Hitchcock Parkway",
        "address_2": null,
        "city": "Aiken",
        "state": "SC",
        "postal_code": "29801",
        "geo_coordinate": "POINT (-81.7792336 33.5543848)"
    },
    "contact": {
        "website": {
            "url": "http:\/\/www.coldcreeknurseries.net\/",
            "title": null,
            "attributes": []
        },
        "email": null,
        "phone": "803-648-3592",
        "fax": null,
        "name": null
    },
    "specialties": [
        {
            "machine_name": "ground_covers",
            "type": "nursery_category",
            "archival_data": {
                "id": "216168"
            }
        },
        {
            "machine_name": "shrubs",
            "type": "nursery_category",
            "archival_data": {
                "id": "216184"
            }
        },
        {
            "machine_name": "trees",
            "type": "nursery_category",
            "archival_data": {
                "id": "216185"
            }
        }
    ],
    "catalog": {
        "print": false,
        "online": true,
        "web_only": true
    },
    "update": null,
    "nursery_catalog_items": [],
    "archival_data": {
        "id": "1673425",
        "legacy_id": "30903",
        "ships": true,
        "NODATE": false,
        "NoCatalog": true,
        "active": true,
        "bulkmail": false,
        "SRCE2000": null,
        "author": "oitadmin",
        "created": "1474897990"
    }
}
