{
    "name": "New England Bonsai Gardens (W)",
    "machine_name": "new_england_bonsai_gardens_w",
    "type": "nursery",
    "retail_wholesale": {
        "retail": false,
        "wholesale": true
    },
    "location": {
        "country": {
            "united_states": true,
            "canada": false
        },
        "address_1": "914 South Main Street",
        "address_2": null,
        "city": "Bellingham",
        "state": "MA",
        "postal_code": "02019-1846",
        "geo_coordinate": "POINT (-71.4839425 42.0625577)"
    },
    "contact": {
        "website": {
            "url": "https:\/\/nebonsai.com\/home\/wholesale\/",
            "title": null,
            "attributes": []
        },
        "email": null,
        "phone": "508-883-2842",
        "fax": "508-883-2862",
        "name": null
    },
    "specialties": [
        {
            "machine_name": "bonsai",
            "type": "nursery_category",
            "archival_data": {
                "id": "216155"
            }
        }
    ],
    "catalog": {
        "print": false,
        "online": true,
        "web_only": true
    },
    "update": null,
    "nursery_catalog_items": [],
    "archival_data": {
        "id": "1672309",
        "legacy_id": "6528",
        "ships": true,
        "NODATE": false,
        "NoCatalog": true,
        "active": true,
        "bulkmail": false,
        "SRCE2000": null,
        "author": "oitadmin",
        "created": "1474897990"
    }
}
